LICENSE.txt
MANIFEST.in
README.md
mrpt.py
pyproject.toml
setup.py
cpp/Mrpt.h
cpp/mrptmodule.cpp
cpp/lib/Eigen/AccelerateSupport
cpp/lib/Eigen/Cholesky
cpp/lib/Eigen/CholmodSupport
cpp/lib/Eigen/Core
cpp/lib/Eigen/Dense
cpp/lib/Eigen/Eigen
cpp/lib/Eigen/Eigenvalues
cpp/lib/Eigen/Geometry
cpp/lib/Eigen/Householder
cpp/lib/Eigen/IterativeLinearSolvers
cpp/lib/Eigen/Jacobi
cpp/lib/Eigen/KLUSupport
cpp/lib/Eigen/LU
cpp/lib/Eigen/MetisSupport
cpp/lib/Eigen/OrderingMethods
cpp/lib/Eigen/PaStiXSupport
cpp/lib/Eigen/PardisoSupport
cpp/lib/Eigen/QR
cpp/lib/Eigen/QtAlignedMalloc
cpp/lib/Eigen/SPQRSupport
cpp/lib/Eigen/SVD
cpp/lib/Eigen/Sparse
cpp/lib/Eigen/SparseCholesky
cpp/lib/Eigen/SparseCore
cpp/lib/Eigen/SparseLU
cpp/lib/Eigen/SparseQR
cpp/lib/Eigen/StdDeque
cpp/lib/Eigen/StdList
cpp/lib/Eigen/StdVector
cpp/lib/Eigen/SuperLUSupport
cpp/lib/Eigen/ThreadPool
cpp/lib/Eigen/UmfPackSupport
cpp/lib/Eigen/src/AccelerateSupport/AccelerateSupport.h
cpp/lib/Eigen/src/AccelerateSupport/InternalHeaderCheck.h
cpp/lib/Eigen/src/Cholesky/InternalHeaderCheck.h
cpp/lib/Eigen/src/Cholesky/LDLT.h
cpp/lib/Eigen/src/Cholesky/LLT.h
cpp/lib/Eigen/src/Cholesky/LLT_LAPACKE.h
cpp/lib/Eigen/src/CholmodSupport/CholmodSupport.h
cpp/lib/Eigen/src/CholmodSupport/InternalHeaderCheck.h
cpp/lib/Eigen/src/Core/ArithmeticSequence.h
cpp/lib/Eigen/src/Core/Array.h
cpp/lib/Eigen/src/Core/ArrayBase.h
cpp/lib/Eigen/src/Core/ArrayWrapper.h
cpp/lib/Eigen/src/Core/Assign.h
cpp/lib/Eigen/src/Core/AssignEvaluator.h
cpp/lib/Eigen/src/Core/Assign_MKL.h
cpp/lib/Eigen/src/Core/BandMatrix.h
cpp/lib/Eigen/src/Core/Block.h
cpp/lib/Eigen/src/Core/CommaInitializer.h
cpp/lib/Eigen/src/Core/ConditionEstimator.h
cpp/lib/Eigen/src/Core/CoreEvaluators.h
cpp/lib/Eigen/src/Core/CoreIterators.h
cpp/lib/Eigen/src/Core/CwiseBinaryOp.h
cpp/lib/Eigen/src/Core/CwiseNullaryOp.h
cpp/lib/Eigen/src/Core/CwiseTernaryOp.h
cpp/lib/Eigen/src/Core/CwiseUnaryOp.h
cpp/lib/Eigen/src/Core/CwiseUnaryView.h
cpp/lib/Eigen/src/Core/DenseBase.h
mrpt.egg-info/PKG-INFO
mrpt.egg-info/SOURCES.txt
mrpt.egg-info/dependency_links.txt
mrpt.egg-info/not-zip-safe
mrpt.egg-info/requires.txt
mrpt.egg-info/top_level.txt